gitOgit/__init__.py
gitOgit/cli.py
gitOgit/gitOgit.py
gitOgit-0.1.1.dist-info/LICENSE
gitOgit-0.1.1.dist-info/METADATA
gitOgit-0.1.1.dist-info/WHEEL
gitOgit-0.1.1.dist-info/entry_points.txt
gitOgit-0.1.1.dist-info/top_level.txt
gitOgit-0.1.1.dist-info/RECORD
